scrapy_feedexporter_azure_blob/__init__.py
scrapy_feedexporter_azure_blob-0.2.dist-info/DESCRIPTION.rst
scrapy_feedexporter_azure_blob-0.2.dist-info/METADATA
scrapy_feedexporter_azure_blob-0.2.dist-info/RECORD
scrapy_feedexporter_azure_blob-0.2.dist-info/WHEEL
scrapy_feedexporter_azure_blob-0.2.dist-info/metadata.json
scrapy_feedexporter_azure_blob-0.2.dist-info/top_level.txt
