Metadata-Version: 2.0
Name: scrapy-feedexporter-azure-blob
Version: 0.2
Summary: Scrapy extension Feed Exporter Storage Backend to export items to a Azure blob container
Home-page: https://github.com/undernewmanagement/scrapy-feedexporter-azure-blob
Author: Mark Anderson
Author-email: mark@m3b.net
License: MIT
Platform: UNKNOWN
Classifier: Framework :: Scrapy
Classifier: Development Status :: 3 - Alpha
Classifier: Environment :: Console
Classifier: Intended Audience :: Developers
Classifier: License :: OSI Approved :: BSD License
Classifier: Operating System :: OS Independent
Classifier: Programming Language :: Python
Classifier: Programming Language :: Python :: 2
Classifier: Programming Language :: Python :: 2.7
Classifier: Topic :: Utilities
Classifier: Framework :: Scrapy
Requires-Dist: azure-storage
